optimaladj/CausalGraph.py
optimaladj/__init__.py
tests/__init__.py
tests/examples.py
tests/test_CausalGraph.py
optimaladj-0.0.4.dist-info/LICENSE
optimaladj-0.0.4.dist-info/METADATA
optimaladj-0.0.4.dist-info/WHEEL
optimaladj-0.0.4.dist-info/top_level.txt
optimaladj-0.0.4.dist-info/RECORD
