Metadata-Version: 2.1
Name: optimaladj
Version: 0.0.4
Summary: A package to compute optimal adjustment sets in causal graphs
Home-page: https://github.com/facusapienza21/optimaladj
Author: Facundo Sapienza, Ezequiel Smucler
Author-email: ezequiels.90@gmail.com
License: UNKNOWN
Platform: UNKNOWN
Classifier: Programming Language :: Python :: 3
Classifier: License :: OSI Approved :: MIT License
Classifier: Operating System :: OS Independent
Requires-Python: >=3.6
License-File: LICENSE
